<?xml version="1.0" encoding="UTF-8"?>
<MatchResult updateDate="2015-03-31" updateTime="12:38:49"><XSN>10</XSN><SportsCode>FB</SportsCode><Match num="1001" ID="65425"><Status>FinalResultIn</Status><Result><Section no="1" date="2015-03-31" time="07:10:11">0:0</Section><Section no="2" date="2015-03-31" time="07:10:11">1:0</Section><Section no="999" date="2015-03-31" time="07:10:11">1:0</Section></Result></Match><Match num="1003" ID="65427"><Status>FinalResultIn</Status><Result><Section no="1" date="2015-03-31" time="10:58:16">0:0</Section><Section no="2" date="2015-03-31" time="10:58:16">0:0</Section><Section no="999" date="2015-03-31" time="10:58:16">0:0</Section></Result></Match><Match num="1004" ID="65428"><Status>FinalResultIn</Status><Result><Section no="1" date="2015-03-31" time="11:12:02">1:1</Section><Section no="2" date="2015-03-31" time="11:12:02">1:1</Section><Section no="999" date="2015-03-31" time="11:12:02">1:1</Section></Result></Match><Match num="6001" ID="65347"><Status>Conclude</Status><Result><Section no="1" date="2015-03-28" time="15:40:44">0:0</Section><Section no="2" date="2015-03-28" time="15:40:44">0:0</Section><Section no="999" date="2015-03-28" time="15:40:44">0:0</Section></Result></Match><Match num="6002" ID="65348"><Status>Conclude</Status><Result><Section no="1" date="2015-03-28" time="15:42:40">3:0</Section><Section no="2" date="2015-03-28" time="15:42:40">3:2</Section><Section no="999" date="2015-03-28" time="15:42:40">3:2</Section></Result></Match><Match num="6003" ID="65349"><Status>Conclude</Status><Result><Section no="1" date="2015-03-28" time="15:43:31">0:0</Section><Section no="2" date="2015-03-28" time="15:43:31">2:0</Section><Section no="999" date="2015-03-28" time="15:43:31">2:0</Section></Result></Match><Match num="6004" ID="65350"><Status>Conclude</Status><Result><Section no="1" date="2015-03-28" time="18:26:29">1:0</Section><Section no="2" date="2015-03-28" time="18:26:29">1:1</Section><Section no="999" date="2015-03-28" time="18:26:29">1:1</Section></Result></Match><Match num="6005" ID="65351"><Status>Conclude</Status><Result><Section no="1" date="2015-03-28" time="18:27:17">0:0</Section><Section no="2" date="2015-03-28" time="18:27:17">0:0</Section><Section no="999" date="2015-03-28" time="18:27:17">0:0</Section></Result></Match><Match num="6006" ID="65352"><Status>Conclude</Status><Result><Section no="1" date="2015-03-28" time="18:28:20">1:0</Section><Section no="2" date="2015-03-28" time="18:28:20">3:1</Section><Section no="999" date="2015-03-28" time="18:28:20">3:1</Section></Result></Match><Match num="6007" ID="65353"><Status>Conclude</Status><Result><Section no="1" date="2015-03-28" time="18:52:26">1:0</Section><Section no="2" date="2015-03-28" time="18:52:26">1:0</Section><Section no="999" date="2015-03-28" time="18:52:26">1:0</Section></Result></Match><Match num="6008" ID="65354"><Status>Conclude</Status><Result><Section no="1" date="2015-03-28" time="20:57:18">0:1</Section><Section no="2" date="2015-03-28" time="20:57:18">3:2</Section><Section no="999" date="2015-03-28" time="20:57:18">3:2</Section></Result></Match><Match num="6009" ID="65355"><Status>Conclude</Status><Result><Section no="1" date="2015-03-29" time="07:15:06">0:2</Section><Section no="2" date="2015-03-29" time="07:15:06">0:3</Section><Section no="999" date="2015-03-29" time="07:15:06">0:3</Section></Result></Match><Match num="6010" ID="65356"><Status>Conclude</Status><Result><Section no="1" date="2015-03-29" time="07:16:40">0:0</Section><Section no="2" date="2015-03-29" time="07:16:40">2:0</Section><Section no="999" date="2015-03-29" time="07:16:40">2:0</Section></Result></Match><Match num="6011" ID="65357"><Status>Conclude</Status><Result><Section no="1" date="2015-03-29" time="07:19:16">1:1</Section><Section no="2" date="2015-03-29" time="07:19:16">2:2</Section><Section no="999" date="2015-03-29" time="07:19:16">2:2</Section></Result></Match><Match num="6012" ID="65358"><Status>Conclude</Status><Result><Section no="1" date="2015-03-29" time="07:19:58">0:0</Section><Section no="2" date="2015-03-29" time="07:19:58">1:0</Section><Section no="999" date="2015-03-29" time="07:19:58">1:0</Section></Result></Match><Match num="6013" ID="65359"><Status>Conclude</Status><Result><Section no="1" date="2015-03-29" time="07:21:16">0:1</Section><Section no="2" date="2015-03-29" time="07:21:16">1:2</Section><Section no="999" date="2015-03-29" time="07:21:16">1:2</Section></Result></Match><Match num="6014" ID="65360"><Status>Conclude</Status><Result><Section no="1" date="2015-03-29" time="07:21:59">0:1</Section><Section no="2" date="2015-03-29" time="07:21:59">3:1</Section><Section no="999" date="2015-03-29" time="07:21:59">3:1</Section></Result></Match><Match num="6015" ID="65361"><Status>Conclude</Status><Result><Section no="1" date="2015-03-29" time="07:22:49">1:1</Section><Section no="2" date="2015-03-29" time="07:22:49">2:2</Section><Section no="999" date="2015-03-29" time="07:22:49">2:2</Section></Result></Match><Match num="6016" ID="65362"><Status>Conclude</Status><Result><Section no="1" date="2015-03-29" time="07:23:55">0:0</Section><Section no="2" date="2015-03-29" time="07:23:55">0:1</Section><Section no="999" date="2015-03-29" time="07:23:55">0:1</Section></Result></Match><Match num="6017" ID="65363"><Status>Conclude</Status><Result><Section no="1" date="2015-03-29" time="07:25:12">0:0</Section><Section no="2" date="2015-03-29" time="07:25:12">2:1</Section><Section no="999" date="2015-03-29" time="07:25:12">2:1</Section></Result></Match><Match num="6018" ID="65364"><Status>Conclude</Status><Result><Section no="1" date="2015-03-29" time="07:26:14">0:1</Section><Section no="2" date="2015-03-29" time="07:26:14">1:2</Section><Section no="999" date="2015-03-29" time="07:26:14">1:2</Section></Result></Match><Match num="6019" ID="65365"><Status>Conclude</Status><Result><Section no="1" date="2015-03-29" time="07:26:49">0:1</Section><Section no="2" date="2015-03-29" time="07:26:49">1:1</Section><Section no="999" date="2015-03-29" time="07:26:49">1:1</Section></Result></Match><Match num="6020" ID="65366"><Status>Conclude</Status><Result><Section no="1" date="2015-03-29" time="07:27:49">1:0</Section><Section no="2" date="2015-03-29" time="07:27:49">2:0</Section><Section no="999" date="2015-03-29" time="07:27:49">2:0</Section></Result></Match><Match num="6021" ID="65367"><Status>Conclude</Status><Result><Section no="1" date="2015-03-29" time="07:28:29">1:0</Section><Section no="2" date="2015-03-29" time="07:28:29">5:1</Section><Section no="999" date="2015-03-29" time="07:28:29">5:1</Section></Result></Match><Match num="6022" ID="65368"><Status>Conclude</Status><Result><Section no="1" date="2015-03-29" time="07:29:13">0:1</Section><Section no="2" date="2015-03-29" time="07:29:13">0:3</Section><Section no="999" date="2015-03-29" time="07:29:13">0:3</Section></Result></Match><Match num="6023" ID="65369"><Status>Conclude</Status><Result><Section no="1" date="2015-03-29" time="07:31:34">0:0</Section><Section no="2" date="2015-03-29" time="07:31:34">0:0</Section><Section no="999" date="2015-03-29" time="07:31:34">0:0</Section></Result></Match><Match num="6024" ID="65370"><Status>Conclude</Status><Result><Section no="1" date="2015-03-29" time="07:32:09">1:2</Section><Section no="2" date="2015-03-29" time="07:32:09">1:4</Section><Section no="999" date="2015-03-29" time="07:32:09">1:4</Section></Result></Match><Match num="6025" ID="65371"><Status>Conclude</Status><Result><Section no="1" date="2015-03-29" time="07:32:39">2:0</Section><Section no="2" date="2015-03-29" time="07:32:39">2:1</Section><Section no="999" date="2015-03-29" time="07:32:39">2:1</Section></Result></Match><Match num="6026" ID="65372"><Status>Conclude</Status><Result><Section no="1" date="2015-03-29" time="07:33:10">0:1</Section><Section no="2" date="2015-03-29" time="07:33:10">1:1</Section><Section no="999" date="2015-03-29" time="07:33:10">1:1</Section></Result></Match><Match num="6027" ID="65373"><Status>Conclude</Status><Result><Section no="1" date="2015-03-29" time="07:33:41">0:1</Section><Section no="2" date="2015-03-29" time="07:33:41">0:3</Section><Section no="999" date="2015-03-29" time="07:33:41">0:3</Section></Result></Match><Match num="6028" ID="65374"><Status>Conclude</Status><Result><Section no="1" date="2015-03-29" time="07:34:11">2:0</Section><Section no="2" date="2015-03-29" time="07:34:11">5:0</Section><Section no="999" date="2015-03-29" time="07:34:11">5:0</Section></Result></Match><Match num="6029" ID="65375"><Status>Conclude</Status><Result><Section no="1" date="2015-03-29" time="07:34:53">2:1</Section><Section no="2" date="2015-03-29" time="07:34:53">2:2</Section><Section no="999" date="2015-03-29" time="07:34:53">2:2</Section></Result></Match><Match num="6030" ID="65376"><Status>Conclude</Status><Result><Section no="1" date="2015-03-29" time="08:31:52">0:0</Section><Section no="2" date="2015-03-29" time="08:31:52">0:1</Section><Section no="999" date="2015-03-29" time="08:31:52">0:1</Section></Result></Match><Match num="6031" ID="65377"><Status>Conclude</Status><Result><Section no="1" date="2015-03-29" time="07:35:18">2:2</Section><Section no="2" date="2015-03-29" time="07:35:18">2:2</Section><Section no="999" date="2015-03-29" time="07:35:18">2:2</Section></Result></Match><Match num="6032" ID="65378"><Status>Conclude</Status><Result><Section no="1" date="2015-03-29" time="08:33:04">0:0</Section><Section no="2" date="2015-03-29" time="08:33:04">0:2</Section><Section no="999" date="2015-03-29" time="08:33:04">0:2</Section></Result></Match><Match num="6033" ID="65379"><Status>Conclude</Status><Result><Section no="1" date="2015-03-29" time="09:32:36">0:0</Section><Section no="2" date="2015-03-29" time="09:32:36">1:0</Section><Section no="999" date="2015-03-29" time="09:32:36">1:0</Section></Result></Match><Match num="6034" ID="65380"><Status>Conclude</Status><Result><Section no="1" date="2015-03-29" time="09:33:09">0:0</Section><Section no="2" date="2015-03-29" time="09:33:09">1:0</Section><Section no="999" date="2015-03-29" time="09:33:09">1:0</Section></Result></Match><Match num="6035" ID="65381"><Status>Conclude</Status><Result><Section no="1" date="2015-03-29" time="09:33:33">0:1</Section><Section no="2" date="2015-03-29" time="09:33:33">0:1</Section><Section no="999" date="2015-03-29" time="09:33:33">0:1</Section></Result></Match><Match num="6036" ID="65382"><Status>Conclude</Status><Result><Section no="1" date="2015-03-29" time="09:34:06">1:1</Section><Section no="2" date="2015-03-29" time="09:34:06">2:2</Section><Section no="999" date="2015-03-29" time="09:34:06">2:2</Section></Result></Match><Match num="6037" ID="65383"><Status>Conclude</Status><Result><Section no="1" date="2015-03-29" time="12:59:38">1:0</Section><Section no="2" date="2015-03-29" time="12:59:38">4:0</Section><Section no="999" date="2015-03-29" time="12:59:38">4:0</Section></Result></Match><Match num="6038" ID="65384"><Status>Conclude</Status><Result><Section no="1" date="2015-03-29" time="10:44:58">0:0</Section><Section no="2" date="2015-03-29" time="10:44:58">1:2</Section><Section no="999" date="2015-03-29" time="10:44:58">1:2</Section></Result></Match><Match num="6039" ID="65385"><Status>Conclude</Status><Result><Section no="1" date="2015-03-29" time="13:01:55">1:0</Section><Section no="2" date="2015-03-29" time="13:01:55">1:0</Section><Section no="999" date="2015-03-29" time="13:01:55">1:0</Section></Result></Match><Match num="6040" ID="65386"><Status>Conclude</Status><Result><Section no="1" date="2015-03-29" time="10:45:23">1:0</Section><Section no="2" date="2015-03-29" time="10:45:23">2:1</Section><Section no="999" date="2015-03-29" time="10:45:23">2:1</Section></Result></Match><Match num="6041" ID="65387"><Status>Conclude</Status><Result><Section no="1" date="2015-03-29" time="11:01:10">0:0</Section><Section no="2" date="2015-03-29" time="11:01:10">0:0</Section><Section no="999" date="2015-03-29" time="11:01:10">0:0</Section></Result></Match><Match num="6042" ID="65388"><Status>Conclude</Status><Result><Section no="1" date="2015-03-29" time="11:01:37">0:0</Section><Section no="2" date="2015-03-29" time="11:01:37">0:0</Section><Section no="999" date="2015-03-29" time="11:01:37">0:0</Section></Result></Match><Match num="6043" ID="65389"><Status>Conclude</Status><Result><Section no="1" date="2015-03-29" time="13:03:23">1:0</Section><Section no="2" date="2015-03-29" time="13:03:23">1:0</Section><Section no="999" date="2015-03-29" time="13:03:23">1:0</Section></Result></Match><Match num="7001" ID="65390"><Status>Conclude</Status><Result><Section no="1" date="2015-03-29" time="14:27:27">0:3</Section><Section no="2" date="2015-03-29" time="14:27:27">0:3</Section><Section no="999" date="2015-03-29" time="14:27:27">0:3</Section></Result></Match><Match num="7002" ID="65391"><Status>Conclude</Status><Result><Section no="1" date="2015-03-29" time="14:28:12">0:0</Section><Section no="2" date="2015-03-29" time="14:28:12">1:0</Section><Section no="999" date="2015-03-29" time="14:28:12">1:0</Section></Result></Match><Match num="7003" ID="65392"><Status>Conclude</Status><Result><Section no="1" date="2015-03-29" time="14:29:14">1:1</Section><Section no="2" date="2015-03-29" time="14:29:14">2:1</Section><Section no="999" date="2015-03-29" time="14:29:14">2:1</Section></Result></Match><Match num="7004" ID="65393"><Status>Conclude</Status><Result><Section no="1" date="2015-03-29" time="14:29:58">2:0</Section><Section no="2" date="2015-03-29" time="14:29:58">3:1</Section><Section no="999" date="2015-03-29" time="14:29:58">3:1</Section></Result></Match><Match num="7005" ID="65394"><Status>Conclude</Status><Result><Section no="1" date="2015-03-29" time="14:22:17">1:0</Section><Section no="2" date="2015-03-29" time="14:22:17">2:1</Section><Section no="999" date="2015-03-29" time="14:22:17">2:1</Section></Result></Match><Match num="7006" ID="65395"><Status>Conclude</Status><Result><Section no="1" date="2015-03-29" time="14:24:01">1:1</Section><Section no="2" date="2015-03-29" time="14:24:01">1:1</Section><Section no="999" date="2015-03-29" time="14:24:01">1:1</Section></Result></Match><Match num="7007" ID="65396"><Status>Conclude</Status><Result><Section no="1" date="2015-03-29" time="14:26:05">0:0</Section><Section no="2" date="2015-03-29" time="14:26:05">0:2</Section><Section no="999" date="2015-03-29" time="14:26:05">0:2</Section></Result></Match><Match num="7008" ID="65397"><Status>Conclude</Status><Result><Section no="1" date="2015-03-29" time="15:13:07">0:0</Section><Section no="2" date="2015-03-29" time="15:13:07">1:1</Section><Section no="999" date="2015-03-29" time="15:13:07">1:1</Section></Result></Match><Match num="7009" ID="65398"><Status>Conclude</Status><Result><Section no="1" date="2015-03-29" time="16:26:02">0:1</Section><Section no="2" date="2015-03-29" time="16:26:02">0:1</Section><Section no="999" date="2015-03-29" time="16:26:02">0:1</Section></Result></Match><Match num="7010" ID="65399"><Status>Conclude</Status><Result><Section no="1" date="2015-03-29" time="16:26:46">0:0</Section><Section no="2" date="2015-03-29" time="16:26:46">0:1</Section><Section no="999" date="2015-03-29" time="16:26:46">0:1</Section></Result></Match><Match num="7011" ID="65400"><Status>Conclude</Status><Result><Section no="1" date="2015-03-29" time="17:39:31">0:0</Section><Section no="2" date="2015-03-29" time="17:39:31">2:0</Section><Section no="999" date="2015-03-29" time="17:39:31">2:0</Section></Result></Match><Match num="7012" ID="65401"><Status>Conclude</Status><Result><Section no="1" date="2015-03-29" time="17:40:09">0:0</Section><Section no="2" date="2015-03-29" time="17:40:09">1:0</Section><Section no="999" date="2015-03-29" time="17:40:09">1:0</Section></Result></Match><Match num="7013" ID="65402"><Status>Conclude</Status><Result><Section no="1" date="2015-03-29" time="17:40:49">1:1</Section><Section no="2" date="2015-03-29" time="17:40:49">1:1</Section><Section no="999" date="2015-03-29" time="17:40:49">1:1</Section></Result></Match><Match num="7014" ID="65403"><Status>Conclude</Status><Result><Section no="1" date="2015-03-29" time="23:36:07">0:1</Section><Section no="2" date="2015-03-29" time="23:36:07">1:1</Section><Section no="999" date="2015-03-29" time="23:36:07">1:1</Section></Result></Match><Match num="7015" ID="65404"><Status>Conclude</Status><Result><Section no="1" date="2015-03-30" time="07:37:05">0:0</Section><Section no="2" date="2015-03-30" time="07:37:05">1:0</Section><Section no="999" date="2015-03-30" time="07:37:05">1:0</Section></Result></Match><Match num="7016" ID="65405"><Status>Conclude</Status><Result><Section no="1" date="2015-03-30" time="07:37:38">0:2</Section><Section no="2" date="2015-03-30" time="07:37:38">0:2</Section><Section no="999" date="2015-03-30" time="07:37:38">0:2</Section></Result></Match><Match num="7017" ID="65406"><Status>Conclude</Status><Result><Section no="1" date="2015-03-30" time="07:38:22">4:1</Section><Section no="2" date="2015-03-30" time="07:38:22">6:1</Section><Section no="999" date="2015-03-30" time="07:38:22">6:1</Section></Result></Match><Match num="7018" ID="65407"><Status>Conclude</Status><Result><Section no="1" date="2015-03-30" time="07:39:09">2:0</Section><Section no="2" date="2015-03-30" time="07:39:09">2:1</Section><Section no="999" date="2015-03-30" time="07:39:09">2:1</Section></Result></Match><Match num="7019" ID="65408"><Status>Conclude</Status><Result><Section no="1" date="2015-03-30" time="07:39:35">1:0</Section><Section no="2" date="2015-03-30" time="07:39:35">1:0</Section><Section no="999" date="2015-03-30" time="07:39:35">1:0</Section></Result></Match><Match num="7020" ID="65409"><Status>Conclude</Status><Result><Section no="1" date="2015-03-30" time="07:40:06">0:1</Section><Section no="2" date="2015-03-30" time="07:40:06">2:1</Section><Section no="999" date="2015-03-30" time="07:40:06">2:1</Section></Result></Match><Match num="7021" ID="65410"><Status>Conclude</Status><Result><Section no="1" date="2015-03-30" time="07:40:38">2:0</Section><Section no="2" date="2015-03-30" time="07:40:38">2:0</Section><Section no="999" date="2015-03-30" time="07:40:38">2:0</Section></Result></Match><Match num="7022" ID="65411"><Status>Conclude</Status><Result><Section no="1" date="2015-03-30" time="07:41:01">0:1</Section><Section no="2" date="2015-03-30" time="07:41:01">1:1</Section><Section no="999" date="2015-03-30" time="07:41:01">1:1</Section></Result></Match><Match num="7023" ID="65412"><Status>Conclude</Status><Result><Section no="1" date="2015-03-30" time="07:41:25">0:0</Section><Section no="2" date="2015-03-30" time="07:41:25">0:0</Section><Section no="999" date="2015-03-30" time="07:41:25">0:0</Section></Result></Match><Match num="7024" ID="65413"><Status>Conclude</Status><Result><Section no="1" date="2015-03-30" time="07:41:54">1:0</Section><Section no="2" date="2015-03-30" time="07:41:54">2:1</Section><Section no="999" date="2015-03-30" time="07:41:54">2:1</Section></Result></Match><Match num="7025" ID="65414"><Status>Conclude</Status><Result><Section no="1" date="2015-03-30" time="07:42:33">0:1</Section><Section no="2" date="2015-03-30" time="07:42:33">0:1</Section><Section no="999" date="2015-03-30" time="07:42:33">0:1</Section></Result></Match><Match num="7026" ID="65415"><Status>Conclude</Status><Result><Section no="1" date="2015-03-30" time="07:43:10">0:0</Section><Section no="2" date="2015-03-30" time="07:43:10">3:0</Section><Section no="999" date="2015-03-30" time="07:43:10">3:0</Section></Result></Match><Match num="7027" ID="65416"><Status>Conclude</Status><Result><Section no="1" date="2015-03-30" time="07:43:31">1:0</Section><Section no="2" date="2015-03-30" time="07:43:31">2:0</Section><Section no="999" date="2015-03-30" time="07:43:31">2:0</Section></Result></Match><Match num="7028" ID="65417"><Status>Conclude</Status><Result><Section no="1" date="2015-03-30" time="07:43:55">2:0</Section><Section no="2" date="2015-03-30" time="07:43:55">2:0</Section><Section no="999" date="2015-03-30" time="07:43:55">2:0</Section></Result></Match><Match num="7029" ID="65418"><Status>Conclude</Status><Result><Section no="1" date="2015-03-30" time="07:44:21">1:0</Section><Section no="2" date="2015-03-30" time="07:44:21">1:0</Section><Section no="999" date="2015-03-30" time="07:44:21">1:0</Section></Result></Match><Match num="7030" ID="65419"><Status>Conclude</Status><Result><Section no="1" date="2015-03-30" time="08:33:22">2:0</Section><Section no="2" date="2015-03-30" time="08:33:22">3:0</Section><Section no="999" date="2015-03-30" time="08:33:22">3:0</Section></Result></Match><Match num="7031" ID="65420"><Status>Conclude</Status><Result><Section no="1" date="2015-03-30" time="08:34:00">1:0</Section><Section no="2" date="2015-03-30" time="08:34:00">1:0</Section><Section no="999" date="2015-03-30" time="08:34:00">1:0</Section></Result></Match><Match num="7032" ID="65421"><Status>Conclude</Status><Result><Section no="1" date="2015-03-30" time="09:11:01">2:0</Section><Section no="2" date="2015-03-30" time="09:11:01">2:0</Section><Section no="999" date="2015-03-30" time="09:11:01">2:0</Section></Result></Match><Match num="7033" ID="65422"><Status>Conclude</Status><Result><Section no="1" date="2015-03-30" time="09:11:27">1:1</Section><Section no="2" date="2015-03-30" time="09:11:27">2:2</Section><Section no="999" date="2015-03-30" time="09:11:27">2:2</Section></Result></Match><Match num="7034" ID="65423"><Status>Conclude</Status><Result><Section no="1" date="2015-03-30" time="10:51:48">1:0</Section><Section no="2" date="2015-03-30" time="10:51:48">2:1</Section><Section no="999" date="2015-03-30" time="10:51:48">2:1</Section></Result></Match><Match num="7035" ID="65424"><Status>Conclude</Status><Result><Section no="1" date="2015-03-30" time="11:27:14">0:2</Section><Section no="2" date="2015-03-30" time="11:27:14">2:3</Section><Section no="999" date="2015-03-30" time="11:27:14">2:3</Section></Result></Match></MatchResult>